oura_ring.py
oura_ring-0.3.0.dist-info/LICENSE
oura_ring-0.3.0.dist-info/WHEEL
oura_ring-0.3.0.dist-info/METADATA
oura_ring-0.3.0.dist-info/RECORD
