Metadata-Version: 2.1
Name: oura-ring
Version: 0.3.0
Summary: Tools for acquiring and analyzing Oura API data.
License: MIT
Author: Josh Hejka
Author-email: josh@joshhejka.com
Requires-Python: >=3.10,<4.0
Classifier: License :: OSI Approved :: MIT License
Classifier: Programming Language :: Python :: 3
Classifier: Programming Language :: Python :: 3.10
Classifier: Programming Language :: Python :: 3.11
Requires-Dist: requests (>=2.28.1,<3.0.0)
